aqt/__init__.py
aqt/common/__init__.py
aqt/common/aqt_common.py
aqt/common/aqt_config.py
aqt/common/aqt_config_schedule_test.py
aqt/common/aqt_config_utils.py
aqt/common/emulated_floating_points.py
aqt/common/emulation_utils.py
aqt/jax/__init__.py
aqt/jax/aqt_conv_general.py
aqt/jax/aqt_conv_general_test.py
aqt/jax/aqt_dot_general.py
aqt/jax/aqt_dot_general_test.py
aqt/jax/aqt_matmul.py
aqt/jax/aqt_matmul_test.py
aqt/jax/aqt_ops.py
aqt/jax/aqt_tensor.py
aqt/jax/aqt_tensor_test.py
aqt/jax/aqt_utils.py
aqt/jax/v2/aqt_conv_general.py
aqt/jax/v2/aqt_conv_general_test.py
aqt/jax/v2/aqt_dot_general.py
aqt/jax/v2/aqt_dot_general_test.py
aqt/jax/v2/aqt_quantizer.py
aqt/jax/v2/aqt_ragged_dot.py
aqt/jax/v2/aqt_ragged_dot_test.py
aqt/jax/v2/aqt_tensor.py
aqt/jax/v2/aqt_tensor_test.py
aqt/jax/v2/calibration.py
aqt/jax/v2/config.py
aqt/jax/v2/config_test.py
aqt/jax/v2/stochastic_rounding.py
aqt/jax/v2/stochastic_rounding_test.py
aqt/jax/v2/tiled_dot_general.py
aqt/jax/v2/tiled_dot_general_test.py
aqt/jax/v2/transpose.py
aqt/jax/v2/transpose_test.py
aqt/jax/v2/utils.py
aqt/jax/v2/examples/examples.ipynb
aqt/jax/v2/examples/flax_e2e_model.py
aqt/jax/v2/examples/flax_e2e_model_test.py
aqt/jax/v2/examples/cnn/aqt_utils.py
aqt/jax/v2/examples/cnn/cnn_examples_smoke_test.py
aqt/jax/v2/examples/cnn/cnn_model.py
aqt/jax/v2/examples/cnn/model_utils.py
aqt/jax/v2/examples/cnn/serve_calibrated_ptq.py
aqt/jax/v2/examples/cnn/serve_ptq.py
aqt/jax/v2/examples/cnn/serve_unquantized.py
aqt/jax/v2/extensions/gptq/gptq_dot_general_quantizer.py
aqt/jax/v2/extensions/gptq/gptq_dot_general_quantizer_test.py
aqt/jax/v2/extensions/gptq/examples/gptq_flax_e2e_model.py
aqt/jax/v2/extensions/gptq/examples/gptq_flax_e2e_model_test.py
aqt/jax/v2/flax/aqt_flax.py
aqt/jax/v2/flax/aqt_flax_calibration.py
aqt/jax/v2/flax/aqt_flax_dg_core.py
aqt/jax/v2/flax/aqt_flax_test.py
aqt/jax/v2/flax/delayed_scaling_calibration.py
aqt/jax/v2/flax/freezer.py
aqt/jax/v2/flax/freezer_test.py
aqtp-0.9.0.dist-info/licenses/LICENSE
aqtp-0.9.0.dist-info/WHEEL
aqtp-0.9.0.dist-info/METADATA
aqtp-0.9.0.dist-info/RECORD
