Metadata-Version: 2.4
Name: aqtp
Version: 0.9.0
Summary: Accurate Quantized Training library.
Author-email: Lukasz Lew <lew@google.com>
Requires-Python: >=3.10
Classifier: Development Status :: 3 - Alpha
Classifier: Intended Audience :: Developers
Classifier: Intended Audience :: Science/Research
Classifier: License :: OSI Approved :: Apache Software License
Classifier: Programming Language :: Python :: 3.10
Classifier: Programming Language :: Python :: 3.11
Classifier: Topic :: Scientific/Engineering :: Artificial Intelligence
License-File: LICENSE
Requires-Dist: absl-py
Requires-Dist: jax
Requires-Dist: jaxlib
Requires-Dist: flax
Requires-Dist: pytest ; extra == "test"
Project-URL: Source, https://github.com/google/aqt
Provides-Extra: test
